{"version":"3.8.0","examples":[{"id":"./spec/car_spec.rb[1:1:1]","description":"initializes with two arguments, wheel size and number","full_description":"car #new initializes with two arguments, wheel size and number","status":"passed","file_path":"./spec/car_spec.rb","line_number":7,"run_time":0.002198231,"pending_message":null},{"id":"./spec/car_spec.rb[1:2:1]","description":"has a wheel_size","full_description":"car #wheel_size has a wheel_size","status":"passed","file_path":"./spec/car_spec.rb","line_number":13,"run_time":0.001096982,"pending_message":null},{"id":"./spec/car_spec.rb[1:3:1]","description":"has a wheel_number","full_description":"car #wheel_number has a wheel_number","status":"passed","file_path":"./spec/car_spec.rb","line_number":20,"run_time":0.000105339,"pending_message":null},{"id":"./spec/car_spec.rb[1:4:1]","description":"returns 'VRRROOOOOOOOOOOOOOOOOOOOOOOM!!!!!'","full_description":"car #go returns 'VRRROOOOOOOOOOOOOOOOOOOOOOOM!!!!!'","status":"passed","file_path":"./spec/car_spec.rb","line_number":27,"run_time":8.867e-05,"pending_message":null},{"id":"./spec/car_spec.rb[1:5:1]","description":"returns 'filling up!'","full_description":"car #fill_up_tank returns 'filling up!'","status":"passed","file_path":"./spec/car_spec.rb","line_number":33,"run_time":8.1286e-05,"pending_message":null},{"id":"./spec/vehicle_spec.rb[1:1:1]","description":"initializes with two arguments, wheel size and number","full_description":"Vehicle #new initializes with two arguments, wheel size and number","status":"passed","file_path":"./spec/vehicle_spec.rb","line_number":7,"run_time":0.000148277,"pending_message":null},{"id":"./spec/vehicle_spec.rb[1:2:1]","description":"has a wheel_size","full_description":"Vehicle #wheel_size has a wheel_size","status":"passed","file_path":"./spec/vehicle_spec.rb","line_number":13,"run_time":8.5384e-05,"pending_message":null},{"id":"./spec/vehicle_spec.rb[1:3:1]","description":"has a wheel_number","full_description":"Vehicle #wheel_number has a wheel_number","status":"passed","file_path":"./spec/vehicle_spec.rb","line_number":20,"run_time":0.000338348,"pending_message":null},{"id":"./spec/vehicle_spec.rb[1:4:1]","description":"returns 'vrrrrrrrooom!'","full_description":"Vehicle #go returns 'vrrrrrrrooom!'","status":"passed","file_path":"./spec/vehicle_spec.rb","line_number":27,"run_time":8.8491e-05,"pending_message":null},{"id":"./spec/vehicle_spec.rb[1:5:1]","description":"returns 'filling up!'","full_description":"Vehicle #fill_up_tank returns 'filling up!'","status":"passed","file_path":"./spec/vehicle_spec.rb","line_number":33,"run_time":0.000115664,"pending_message":null}],"summary":{"duration":0.008767491,"example_count":10,"failure_count":0,"pending_count":0,"errors_outside_of_examples_count":0},"summary_line":"10 examples, 0 failures"}